{"info": {"year": "2022", "date_created": "2022-03-18"}, "categories": [{"supercategory": null, "name": "BACKGROUND", "id": 0}, {"supercategory": null, "name": "NUCLEUS", "id": 1}, {"supercategory": null, "name": "CLUSTER", "id": 2}, {"supercategory": null, "name": "SATELLITE", "id": 3}, {"supercategory": null, "name": "NUCLEUS_OUT_OF_FOCUS", "id": 4}, {"supercategory": null, "name": "OVERLAPPED_NUCLEI", "id": 5}, {"supercategory": null, "name": "NON_VIABLE_NUCLEUS", "id": 6}, {"supercategory": null, "name": "LEUKOCYTE_NUCLEUS", "id": 7}], "images": [{"file_name": "C_13509_-270720_116640", "height": 1200, "width": 1600, "id": 1}, {"file_name": "D_10152_-237600_96120", "height": 1200, "width": 1600, "id": 2}, {"file_name": "E_14415_-324000_127440", "height": 1200, "width": 1600, "id": 3}, {"file_name": "M_2042_-257760_58320", "height": 1200, "width": 1600, "id": 6}, {"file_name": "H_10177_-266400_93960", "height": 1200, "width": 1600, "id": 4}, {"file_name": "K_11984_-262080_116640", "height": 1200, "width": 1600, "id": 5}, {"file_name": "O_1044_-240480_58320", "height": 1200, "width": 1600, "id": 7}], "annotations": [{"image_id": 1, "file_name": "C_13509_-270720_116640.png", "segments_info": [{"id": 13615109, "category_id": 6, "area": 2653, "bbox": [978, 902, 52, 63], "iscrowd": 0}, {"id": 14459935, "category_id": 6, "area": 1799, "bbox": [1154, 598, 51, 48], "iscrowd": 0}, {"id": 13939733, "category_id": 6, "area": 1545, "bbox": [928, 554, 32, 67], "iscrowd": 0}, {"id": 13542416, "category_id": 6, "area": 3669, "bbox": [1355, 886, 67, 68], "iscrowd": 0}, {"id": 14143488, "category_id": 6, "area": 2014, "bbox": [1132, 1088, 52, 48], "iscrowd": 0}, {"id": 12630286, "category_id": 6, "area": 1973, "bbox": [942, 1082, 65, 47], "iscrowd": 0}, {"id": 14987008, "category_id": 6, "area": 1444, "bbox": [958, 1036, 35, 54], "iscrowd": 0}, {"id": 11005466, "category_id": 4, "area": 2595, "bbox": [1107, 479, 61, 52], "iscrowd": 0}, {"id": 4095253, "category_id": 1, "area": 2504, "bbox": [1197, 455, 50, 64], "iscrowd": 0}, {"id": 2783255, "category_id": 1, "area": 2528, "bbox": [1409, 1042, 61, 58], "iscrowd": 0}, {"id": 5400320, "category_id": 1, "area": 4255, "bbox": [1505, 1021, 76, 69], "iscrowd": 0}, {"id": 4617762, "category_id": 1, "area": 2880, "bbox": [1526, 607, 62, 63], "iscrowd": 0}, {"id": 5085223, "category_id": 1, "area": 3173, "bbox": [1524, 548, 63, 62], "iscrowd": 0}, {"id": 3832114, "category_id": 1, "area": 2193, "bbox": [1334, 588, 62, 58], "iscrowd": 0}, {"id": 5731119, "category_id": 1, "area": 2524, "bbox": [1045, 631, 61, 55], "iscrowd": 0}, {"id": 4427890, "category_id": 2, "area": 80, "bbox": [1233, 501, 8, 14], "iscrowd": 0}, {"id": 3503245, "category_id": 2, "area": 63, "bbox": [1222, 473, 11, 7], "iscrowd": 0}, {"id": 4028559, "category_id": 2, "area": 44, "bbox": [1436, 1064, 7, 9], "iscrowd": 0}, {"id": 5087082, "category_id": 2, "area": 93, "bbox": [1434, 1086, 12, 10], "iscrowd": 0}, {"id": 4101768, "category_id": 2, "area": 53, "bbox": [1519, 1067, 9, 7], "iscrowd": 0}, {"id": 2730105, "category_id": 2, "area": 171, "bbox": [1531, 1022, 17, 13], "iscrowd": 0}, {"id": 5078914, "category_id": 2, "area": 69, "bbox": [1565, 652, 8, 13], "iscrowd": 0}, {"id": 4227181, "category_id": 2, "area": 68, "bbox": [1538, 632, 10, 9], "iscrowd": 0}, {"id": 4489814, "category_id": 2, "area": 144, "bbox": [1543, 579, 15, 13], "iscrowd": 0}, {"id": 2585948, "category_id": 2, "area": 95, "bbox": [1364, 609, 11, 10], "iscrowd": 0}, {"id": 3764826, "category_id": 2, "area": 60, "bbox": [1079, 663, 9, 9], "iscrowd": 0}, {"id": 10879230, "category_id": 3, "area": 87, "bbox": [1367, 631, 11, 11], "iscrowd": 0}]}, {"image_id": 2, "file_name": "D_10152_-237600_96120.png", "segments_info": [{"id": 255, "category_id": 7, "area": 641, "bbox": [977, 971, 29, 29], "iscrowd": 0}, {"id": 917759, "category_id": 7, "area": 691, "bbox": [968, 996, 33, 26], "iscrowd": 0}, {"id": 11468058, "category_id": 4, "area": 3088, "bbox": [1142, 861, 61, 65], "iscrowd": 0}, {"id": 5465646, "category_id": 1, "area": 5535, "bbox": [599, 1113, 86, 83], "iscrowd": 0}, {"id": 2593792, "category_id": 1, "area": 2703, "bbox": [881, 957, 54, 67], "iscrowd": 0}, {"id": 5220477, "category_id": 2, "area": 48, "bbox": [894, 991, 7, 9], "iscrowd": 0}, {"id": 5545354, "category_id": 2, "area": 77, "bbox": [919, 990, 9, 11], "iscrowd": 0}, {"id": 10424825, "category_id": 3, "area": 87, "bbox": [645, 1139, 11, 11], "iscrowd": 0}, {"id": 11731172, "category_id": 3, "area": 87, "bbox": [648, 1181, 11, 11], "iscrowd": 0}, {"id": 12189937, "category_id": 3, "area": 87, "bbox": [893, 972, 11, 11], "iscrowd": 0}, {"id": 9176575, "category_id": 3, "area": 87, "bbox": [908, 979, 11, 11], "iscrowd": 0}, {"id": 11075839, "category_id": 3, "area": 87, "bbox": [894, 1000, 11, 11], "iscrowd": 0}]}, {"image_id": 3, "file_name": "E_14415_-324000_127440.png", "segments_info": [{"id": 721135, "category_id": 7, "area": 806, "bbox": [1319, 522, 31, 33], "iscrowd": 0}, {"id": 1023, "category_id": 7, "area": 633, "bbox": [1160, 709, 32, 26], "iscrowd": 0}, {"id": 3583, "category_id": 7, "area": 995, "bbox": [930, 600, 34, 38], "iscrowd": 0}, {"id": 1279, "category_id": 7, "area": 682, "bbox": [296, 1099, 24, 35], "iscrowd": 0}, {"id": 5984807, "category_id": 5, "area": 3665, "bbox": [686, 690, 56, 92], "iscrowd": 1}, {"id": 4874535, "category_id": 5, "area": 2333, "bbox": [945, 178, 48, 62], "iscrowd": 1}, {"id": 5864748, "category_id": 1, "area": 4400, "bbox": [116, 273, 84, 70], "iscrowd": 0}, {"id": 3307790, "category_id": 1, "area": 6293, "bbox": [249, 328, 79, 100], "iscrowd": 0}, {"id": 4357120, "category_id": 1, "area": 3948, "bbox": [343, 280, 84, 59], "iscrowd": 0}, {"id": 2654989, "category_id": 1, "area": 2031, "bbox": [650, 218, 71, 37], "iscrowd": 0}, {"id": 5804817, "category_id": 1, "area": 5925, "bbox": [647, 10, 89, 85], "iscrowd": 0}, {"id": 2396672, "category_id": 1, "area": 4343, "bbox": [767, 55, 98, 78], "iscrowd": 0}, {"id": 2187798, "category_id": 1, "area": 5547, "bbox": [1039, 105, 110, 64], "iscrowd": 0}, {"id": 3826961, "category_id": 1, "area": 6108, "bbox": [1146, 162, 95, 80], "iscrowd": 0}, {"id": 5080349, "category_id": 1, "area": 3789, "bbox": [1049, 221, 73, 67], "iscrowd": 0}, {"id": 2712587, "category_id": 1, "area": 7706, "bbox": [1355, 217, 92, 107], "iscrowd": 0}, {"id": 2784799, "category_id": 1, "area": 4269, "bbox": [1045, 1038, 63, 102], "iscrowd": 0}, {"id": 5926658, "category_id": 1, "area": 3254, "bbox": [840, 950, 69, 63], "iscrowd": 0}, {"id": 2715166, "category_id": 1, "area": 6680, "bbox": [333, 157, 95, 87], "iscrowd": 0}, {"id": 6069636, "category_id": 2, "area": 268, "bbox": [147, 289, 16, 22], "iscrowd": 0}, {"id": 5675139, "category_id": 2, "area": 250, "bbox": [275, 366, 15, 23], "iscrowd": 0}, {"id": 3114859, "category_id": 2, "area": 189, "bbox": [291, 362, 15, 16], "iscrowd": 0}, {"id": 5870692, "category_id": 2, "area": 157, "bbox": [391, 300, 13, 15], "iscrowd": 0}, {"id": 6124657, "category_id": 2, "area": 94, "bbox": [397, 316, 13, 9], "iscrowd": 0}, {"id": 4552304, "category_id": 2, "area": 75, "bbox": [679, 231, 10, 9], "iscrowd": 0}, {"id": 4366952, "category_id": 2, "area": 183, "bbox": [654, 50, 16, 15], "iscrowd": 0}, {"id": 5930375, "category_id": 2, "area": 111, "bbox": [693, 70, 12, 13], "iscrowd": 0}, {"id": 5997917, "category_id": 2, "area": 159, "bbox": [782, 65, 13, 16], "iscrowd": 0}, {"id": 3313794, "category_id": 2, "area": 149, "bbox": [806, 101, 14, 14], "iscrowd": 0}, {"id": 2991714, "category_id": 2, "area": 68, "bbox": [815, 115, 9, 9], "iscrowd": 0}, {"id": 2990696, "category_id": 2, "area": 241, "bbox": [1093, 125, 18, 17], "iscrowd": 0}, {"id": 6392452, "category_id": 2, "area": 144, "bbox": [1176, 214, 13, 16], "iscrowd": 0}, {"id": 4893299, "category_id": 2, "area": 72, "bbox": [1200, 208, 10, 10], "iscrowd": 0}, {"id": 5930848, "category_id": 2, "area": 302, "bbox": [1208, 177, 21, 20], "iscrowd": 0}, {"id": 4888926, "category_id": 2, "area": 148, "bbox": [1055, 253, 15, 12], "iscrowd": 0}, {"id": 2783622, "category_id": 2, "area": 65, "bbox": [1088, 269, 10, 9], "iscrowd": 0}, {"id": 6063977, "category_id": 2, "area": 170, "bbox": [1090, 229, 15, 15], "iscrowd": 0}, {"id": 4036708, "category_id": 2, "area": 147, "bbox": [1379, 291, 13, 14], "iscrowd": 0}, {"id": 3836517, "category_id": 2, "area": 242, "bbox": [1416, 254, 14, 22], "iscrowd": 0}, {"id": 3637642, "category_id": 2, "area": 120, "bbox": [1065, 1060, 8, 18], "iscrowd": 0}, {"id": 2592106, "category_id": 2, "area": 62, "bbox": [858, 981, 10, 8], "iscrowd": 0}, {"id": 4094583, "category_id": 2, "area": 130, "bbox": [863, 960, 14, 13], "iscrowd": 0}, {"id": 2861172, "category_id": 2, "area": 195, "bbox": [702, 746, 21, 15], "iscrowd": 0}, {"id": 4100196, "category_id": 2, "area": 154, "bbox": [370, 178, 15, 12], "iscrowd": 0}, {"id": 4429454, "category_id": 2, "area": 228, "bbox": [406, 202, 18, 18], "iscrowd": 0}, {"id": 12059391, "category_id": 3, "area": 87, "bbox": [147, 322, 11, 11], "iscrowd": 0}, {"id": 10688767, "category_id": 3, "area": 87, "bbox": [347, 212, 11, 10], "iscrowd": 0}, {"id": 9248504, "category_id": 3, "area": 87, "bbox": [371, 219, 11, 11], "iscrowd": 0}, {"id": 9569277, "category_id": 3, "area": 87, "bbox": [958, 212, 11, 10], "iscrowd": 0}, {"id": 9437435, "category_id": 3, "area": 87, "bbox": [972, 187, 11, 11], "iscrowd": 0}]}, {"image_id": 6, "file_name": "M_2042_-257760_58320.png", "segments_info": [{"id": 13817100, "category_id": 6, "area": 3070, "bbox": [1306, 386, 77, 77], "iscrowd": 0}, {"id": 10612007, "category_id": 4, "area": 1800, "bbox": [1538, 83, 50, 52], "iscrowd": 0}, {"id": 9165109, "category_id": 4, "area": 1908, "bbox": [469, 799, 51, 48], "iscrowd": 0}, {"id": 3307524, "category_id": 1, "area": 4205, "bbox": [94, 551, 77, 69], "iscrowd": 0}, {"id": 5477909, "category_id": 1, "area": 1773, "bbox": [486, 1149, 50, 47], "iscrowd": 0}, {"id": 3699986, "category_id": 1, "area": 2054, "bbox": [855, 855, 45, 57], "iscrowd": 0}, {"id": 4955736, "category_id": 2, "area": 79, "bbox": [138, 581, 10, 10], "iscrowd": 0}, {"id": 5214860, "category_id": 2, "area": 168, "bbox": [866, 868, 15, 19], "iscrowd": 0}, {"id": 10354943, "category_id": 3, "area": 87, "bbox": [506, 1173, 10, 10], "iscrowd": 0}]}, {"image_id": 4, "file_name": "H_10177_-266400_93960.png", "segments_info": [{"id": 4279602, "category_id": 5, "area": 9437, "bbox": [516, 771, 139, 91], "iscrowd": 1}, {"id": 4022796, "category_id": 5, "area": 4474, "bbox": [297, 560, 61, 97], "iscrowd": 1}, {"id": 5330489, "category_id": 5, "area": 11420, "bbox": [333, 558, 102, 138], "iscrowd": 1}, {"id": 7224641, "category_id": 5, "area": 8317, "bbox": [767, 970, 114, 98], "iscrowd": 1}, {"id": 11663663, "category_id": 4, "area": 3946, "bbox": [233, 902, 74, 71], "iscrowd": 0}, {"id": 9435931, "category_id": 4, "area": 3293, "bbox": [78, 529, 111, 50], "iscrowd": 0}, {"id": 9689344, "category_id": 4, "area": 2459, "bbox": [726, 426, 36, 96], "iscrowd": 0}, {"id": 10940980, "category_id": 4, "area": 9240, "bbox": [610, 940, 97, 123], "iscrowd": 0}, {"id": 5339944, "category_id": 1, "area": 4317, "bbox": [431, 783, 74, 74], "iscrowd": 0}, {"id": 2785799, "category_id": 1, "area": 2502, "bbox": [234, 780, 66, 48], "iscrowd": 0}, {"id": 3512092, "category_id": 1, "area": 2375, "bbox": [166, 859, 47, 68], "iscrowd": 0}, {"id": 4743981, "category_id": 1, "area": 2814, "bbox": [29, 709, 67, 55], "iscrowd": 0}, {"id": 3308294, "category_id": 1, "area": 5195, "bbox": [317, 449, 72, 103], "iscrowd": 0}, {"id": 3114030, "category_id": 1, "area": 6013, "bbox": [1406, 81, 89, 91], "iscrowd": 0}, {"id": 4295717, "category_id": 1, "area": 5432, "bbox": [0, 518, 76, 94], "iscrowd": 0}, {"id": 3973741, "category_id": 2, "area": 44, "bbox": [454, 788, 8, 8], "iscrowd": 0}, {"id": 4957823, "category_id": 2, "area": 54, "bbox": [251, 797, 10, 9], "iscrowd": 0}, {"id": 4104562, "category_id": 2, "area": 80, "bbox": [283, 803, 10, 11], "iscrowd": 0}, {"id": 4291924, "category_id": 2, "area": 79, "bbox": [190, 876, 9, 11], "iscrowd": 0}, {"id": 6326403, "category_id": 2, "area": 48, "bbox": [67, 744, 12, 6], "iscrowd": 0}, {"id": 5469036, "category_id": 2, "area": 110, "bbox": [336, 498, 10, 15], "iscrowd": 0}, {"id": 4295554, "category_id": 2, "area": 52, "bbox": [365, 488, 8, 9], "iscrowd": 0}, {"id": 3903352, "category_id": 2, "area": 47, "bbox": [356, 496, 8, 9], "iscrowd": 0}, {"id": 5549658, "category_id": 2, "area": 41, "bbox": [608, 803, 8, 7], "iscrowd": 0}, {"id": 4039773, "category_id": 2, "area": 43, "bbox": [1441, 123, 8, 7], "iscrowd": 0}, {"id": 6064240, "category_id": 2, "area": 62, "bbox": [339, 522, 8, 10], "iscrowd": 0}, {"id": 4883082, "category_id": 2, "area": 101, "bbox": [807, 987, 12, 11], "iscrowd": 0}, {"id": 2661979, "category_id": 2, "area": 60, "bbox": [332, 563, 9, 8], "iscrowd": 0}, {"id": 5011576, "category_id": 2, "area": 81, "bbox": [35, 579, 10, 11], "iscrowd": 0}, {"id": 11469032, "category_id": 3, "area": 87, "bbox": [466, 801, 11, 11], "iscrowd": 0}, {"id": 9768447, "category_id": 3, "area": 87, "bbox": [465, 846, 11, 11], "iscrowd": 0}, {"id": 9306367, "category_id": 3, "area": 87, "bbox": [69, 716, 11, 11], "iscrowd": 0}, {"id": 9896191, "category_id": 3, "area": 87, "bbox": [524, 784, 11, 11], "iscrowd": 0}, {"id": 10879203, "category_id": 3, "area": 87, "bbox": [605, 813, 11, 11], "iscrowd": 0}, {"id": 10622689, "category_id": 3, "area": 87, "bbox": [629, 835, 11, 11], "iscrowd": 0}, {"id": 12058848, "category_id": 3, "area": 87, "bbox": [564, 801, 11, 11], "iscrowd": 0}, {"id": 9117439, "category_id": 3, "area": 87, "bbox": [583, 839, 11, 11], "iscrowd": 0}, {"id": 10229476, "category_id": 3, "area": 87, "bbox": [1469, 149, 11, 11], "iscrowd": 0}, {"id": 10158335, "category_id": 3, "area": 87, "bbox": [811, 1008, 11, 11], "iscrowd": 0}, {"id": 10230783, "category_id": 3, "area": 87, "bbox": [801, 1028, 11, 11], "iscrowd": 0}, {"id": 10362617, "category_id": 3, "area": 87, "bbox": [776, 986, 11, 11], "iscrowd": 0}, {"id": 12255487, "category_id": 3, "area": 87, "bbox": [375, 582, 11, 11], "iscrowd": 0}, {"id": 12321535, "category_id": 3, "area": 87, "bbox": [374, 560, 11, 11], "iscrowd": 0}]}, {"image_id": 5, "file_name": "K_11984_-262080_116640.png", "segments_info": [{"id": 13810446, "category_id": 6, "area": 5613, "bbox": [951, 517, 85, 84], "iscrowd": 0}, {"id": 12433953, "category_id": 6, "area": 4142, "bbox": [1223, 359, 65, 79], "iscrowd": 0}, {"id": 14540032, "category_id": 6, "area": 6472, "bbox": [976, 273, 101, 87], "iscrowd": 0}, {"id": 5526841, "category_id": 5, "area": 7102, "bbox": [1108, 454, 118, 89], "iscrowd": 1}, {"id": 12451632, "category_id": 4, "area": 4290, "bbox": [1470, 701, 73, 75], "iscrowd": 0}, {"id": 12582656, "category_id": 4, "area": 5310, "bbox": [1287, 678, 81, 83], "iscrowd": 0}, {"id": 11850520, "category_id": 4, "area": 3927, "bbox": [1084, 667, 76, 76], "iscrowd": 0}, {"id": 11655709, "category_id": 4, "area": 4394, "bbox": [1303, 436, 92, 64], "iscrowd": 0}, {"id": 12384809, "category_id": 4, "area": 3971, "bbox": [1537, 502, 60, 89], "iscrowd": 0}, {"id": 4022533, "category_id": 1, "area": 5573, "bbox": [1454, 500, 88, 77], "iscrowd": 0}, {"id": 5803544, "category_id": 1, "area": 3268, "bbox": [1189, 129, 78, 56], "iscrowd": 0}, {"id": 5478190, "category_id": 1, "area": 3816, "bbox": [1286, 864, 86, 56], "iscrowd": 0}, {"id": 4557450, "category_id": 2, "area": 47, "bbox": [1140, 480, 8, 8], "iscrowd": 0}, {"id": 6387035, "category_id": 2, "area": 50, "bbox": [1229, 166, 8, 8], "iscrowd": 0}, {"id": 2922581, "category_id": 2, "area": 67, "bbox": [1351, 878, 10, 9], "iscrowd": 0}, {"id": 9109759, "category_id": 3, "area": 87, "bbox": [1512, 560, 10, 11], "iscrowd": 0}]}, {"image_id": 7, "file_name": "O_1044_-240480_58320.png", "segments_info": [{"id": 1966315, "category_id": 7, "area": 822, "bbox": [1573, 1102, 27, 44], "iscrowd": 0}, {"id": 590079, "category_id": 7, "area": 901, "bbox": [1384, 1082, 28, 39], "iscrowd": 0}, {"id": 1310975, "category_id": 7, "area": 1402, "bbox": [1389, 1115, 51, 35], "iscrowd": 0}, {"id": 4860, "category_id": 7, "area": 2677, "bbox": [1122, 508, 57, 62], "iscrowd": 0}, {"id": 465663, "category_id": 7, "area": 380, "bbox": [1421, 652, 24, 20], "iscrowd": 0}, {"id": 923380, "category_id": 7, "area": 1874, "bbox": [702, 479, 38, 63], "iscrowd": 0}, {"id": 1642232, "category_id": 7, "area": 781, "bbox": [1370, 113, 31, 32], "iscrowd": 0}, {"id": 4607, "category_id": 7, "area": 986, "bbox": [36, 505, 35, 36], "iscrowd": 0}, {"id": 228, "category_id": 7, "area": 353, "bbox": [50, 135, 25, 20], "iscrowd": 0}, {"id": 4863, "category_id": 7, "area": 1234, "bbox": [957, 722, 34, 48], "iscrowd": 0}, {"id": 6699805, "category_id": 5, "area": 3510, "bbox": [1103, 616, 67, 71], "iscrowd": 1}, {"id": 4340020, "category_id": 5, "area": 4615, "bbox": [889, 955, 72, 87], "iscrowd": 1}, {"id": 4863803, "category_id": 5, "area": 7577, "bbox": [1419, 24, 93, 124], "iscrowd": 1}, {"id": 11724583, "category_id": 4, "area": 2341, "bbox": [797, 886, 54, 60], "iscrowd": 0}, {"id": 9955374, "category_id": 4, "area": 2407, "bbox": [730, 978, 72, 44], "iscrowd": 0}, {"id": 12838944, "category_id": 4, "area": 3421, "bbox": [504, 236, 69, 69], "iscrowd": 0}, {"id": 11730715, "category_id": 4, "area": 1772, "bbox": [1277, 966, 45, 54], "iscrowd": 0}, {"id": 2520083, "category_id": 1, "area": 3060, "bbox": [1160, 915, 87, 47], "iscrowd": 0}, {"id": 3959565, "category_id": 1, "area": 2671, "bbox": [1368, 981, 52, 68], "iscrowd": 0}, {"id": 3643693, "category_id": 1, "area": 2083, "bbox": [1542, 940, 54, 57], "iscrowd": 0}, {"id": 4295976, "category_id": 1, "area": 3209, "bbox": [1062, 1143, 125, 57], "iscrowd": 0}, {"id": 5279232, "category_id": 1, "area": 4291, "bbox": [925, 1115, 61, 85], "iscrowd": 0}, {"id": 2854674, "category_id": 1, "area": 5616, "bbox": [843, 1066, 86, 87], "iscrowd": 0}, {"id": 2198576, "category_id": 1, "area": 2161, "bbox": [916, 1059, 53, 52], "iscrowd": 0}, {"id": 2453532, "category_id": 1, "area": 2784, "bbox": [980, 1027, 63, 62], "iscrowd": 0}, {"id": 5863709, "category_id": 1, "area": 2576, "bbox": [786, 1029, 43, 80], "iscrowd": 0}, {"id": 4354857, "category_id": 1, "area": 2942, "bbox": [1015, 973, 72, 52], "iscrowd": 0}, {"id": 3048201, "category_id": 1, "area": 1903, "bbox": [962, 977, 49, 52], "iscrowd": 0}, {"id": 3043613, "category_id": 1, "area": 1805, "bbox": [690, 1024, 38, 61], "iscrowd": 0}, {"id": 4886272, "category_id": 1, "area": 3704, "bbox": [847, 702, 68, 71], "iscrowd": 0}, {"id": 3048448, "category_id": 1, "area": 3510, "bbox": [1386, 511, 69, 65], "iscrowd": 0}, {"id": 3376645, "category_id": 1, "area": 2398, "bbox": [1482, 492, 72, 47], "iscrowd": 0}, {"id": 5398784, "category_id": 1, "area": 5656, "bbox": [409, 44, 69, 104], "iscrowd": 0}, {"id": 2323968, "category_id": 1, "area": 3702, "bbox": [614, 96, 90, 68], "iscrowd": 0}, {"id": 5285238, "category_id": 2, "area": 164, "bbox": [1184, 923, 18, 13], "iscrowd": 0}, {"id": 4172939, "category_id": 2, "area": 57, "bbox": [1216, 940, 9, 8], "iscrowd": 0}, {"id": 3383925, "category_id": 2, "area": 91, "bbox": [1196, 945, 13, 10], "iscrowd": 0}, {"id": 5734776, "category_id": 2, "area": 60, "bbox": [1407, 1009, 9, 8], "iscrowd": 0}, {"id": 4892297, "category_id": 2, "area": 131, "bbox": [1379, 1025, 12, 14], "iscrowd": 0}, {"id": 2461561, "category_id": 2, "area": 46, "bbox": [1559, 981, 7, 9], "iscrowd": 0}, {"id": 6193024, "category_id": 2, "area": 59, "bbox": [1579, 960, 9, 8], "iscrowd": 0}, {"id": 4296022, "category_id": 2, "area": 55, "bbox": [1136, 1167, 9, 7], "iscrowd": 0}, {"id": 2792056, "category_id": 2, "area": 101, "bbox": [1098, 1176, 9, 13], "iscrowd": 0}, {"id": 6400888, "category_id": 2, "area": 211, "bbox": [935, 1151, 18, 15], "iscrowd": 0}, {"id": 5144955, "category_id": 2, "area": 44, "bbox": [946, 1185, 8, 7], "iscrowd": 0}, {"id": 4763277, "category_id": 2, "area": 149, "bbox": [874, 1077, 14, 14], "iscrowd": 0}, {"id": 5480583, "category_id": 2, "area": 165, "bbox": [900, 1114, 15, 15], "iscrowd": 0}, {"id": 3308919, "category_id": 2, "area": 112, "bbox": [883, 1126, 13, 12], "iscrowd": 0}, {"id": 5809244, "category_id": 2, "area": 63, "bbox": [938, 1083, 8, 10], "iscrowd": 0}, {"id": 5018764, "category_id": 2, "area": 100, "bbox": [1007, 1054, 11, 12], "iscrowd": 0}, {"id": 5807491, "category_id": 2, "area": 127, "bbox": [795, 1073, 10, 18], "iscrowd": 0}, {"id": 3180426, "category_id": 2, "area": 46, "bbox": [792, 1047, 8, 8], "iscrowd": 0}, {"id": 5801324, "category_id": 2, "area": 59, "bbox": [1023, 984, 9, 8], "iscrowd": 0}, {"id": 5281673, "category_id": 2, "area": 56, "bbox": [1062, 1000, 10, 8], "iscrowd": 0}, {"id": 5208191, "category_id": 2, "area": 76, "bbox": [986, 998, 9, 10], "iscrowd": 0}, {"id": 6328429, "category_id": 2, "area": 50, "bbox": [699, 1055, 8, 10], "iscrowd": 0}, {"id": 5278603, "category_id": 2, "area": 43, "bbox": [707, 1039, 8, 7], "iscrowd": 0}, {"id": 5146765, "category_id": 2, "area": 103, "bbox": [871, 722, 13, 12], "iscrowd": 0}, {"id": 4423529, "category_id": 2, "area": 82, "bbox": [871, 760, 9, 12], "iscrowd": 0}, {"id": 4102530, "category_id": 2, "area": 75, "bbox": [1125, 634, 10, 10], "iscrowd": 0}, {"id": 4883578, "category_id": 2, "area": 170, "bbox": [1405, 545, 14, 15], "iscrowd": 0}, {"id": 4303970, "category_id": 2, "area": 48, "bbox": [1512, 511, 6, 9], "iscrowd": 0}, {"id": 2665300, "category_id": 2, "area": 86, "bbox": [1506, 497, 13, 10], "iscrowd": 0}, {"id": 3249037, "category_id": 2, "area": 255, "bbox": [452, 80, 14, 24], "iscrowd": 0}, {"id": 3046239, "category_id": 2, "area": 55, "bbox": [441, 82, 8, 10], "iscrowd": 0}, {"id": 3634286, "category_id": 2, "area": 50, "bbox": [672, 133, 8, 8], "iscrowd": 0}, {"id": 4945498, "category_id": 2, "area": 93, "bbox": [676, 115, 11, 10], "iscrowd": 0}, {"id": 3973214, "category_id": 2, "area": 130, "bbox": [1431, 104, 11, 16], "iscrowd": 0}, {"id": 3702396, "category_id": 2, "area": 42, "bbox": [1455, 108, 8, 8], "iscrowd": 0}, {"id": 4299389, "category_id": 2, "area": 67, "bbox": [1494, 52, 8, 11], "iscrowd": 0}, {"id": 3509128, "category_id": 2, "area": 135, "bbox": [932, 977, 15, 12], "iscrowd": 0}, {"id": 5538696, "category_id": 2, "area": 61, "bbox": [894, 999, 10, 9], "iscrowd": 0}, {"id": 4300157, "category_id": 2, "area": 51, "bbox": [927, 1021, 9, 8], "iscrowd": 0}, {"id": 11143420, "category_id": 3, "area": 87, "bbox": [1012, 1004, 11, 11], "iscrowd": 0}, {"id": 10027263, "category_id": 3, "area": 87, "bbox": [653, 132, 11, 11], "iscrowd": 0}]}]}
